pywalrus/__init__.py
pywalrus/walrus.py
pywalrus-0.0.2.dist-info/LICENSE
pywalrus-0.0.2.dist-info/METADATA
pywalrus-0.0.2.dist-info/WHEEL
pywalrus-0.0.2.dist-info/top_level.txt
pywalrus-0.0.2.dist-info/RECORD
